{
  "IsTrans": false,
  "TamerPath": "/Game/00Main/Design/Units/GYCY/Unit_GYCY_YouHun.Unit_GYCY_YouHun_C",
  "BossConf": {
    "CapsuleHalfHeight": 120.0,
    "CapsuleRadius": 50.0,
    "SKMesh": "/Game/00MainHZ/Characters/Enemy/GYCY/GYCY_YouHun/Mesh/SK_GYCY_YouHun.SK_GYCY_YouHun",
    "ABPClass": "/Game/00MainHZ/Characters/Enemy/GYCY/GYCY_YouHun/ABP_GYCY_YouHun.ABP_GYCY_YouHun_C",
    "PhysicsAsset": "/Game/00MainHZ/Characters/Enemy/GYCY/GYCY_YouHun/Mesh/PA_GYCY_YouHun.PA_GYCY_YouHun",
    "Weapons": null,
    "TFXConfigs": null,
    "InteractBones": null,
    "Override_AbnormalDispID_Attacker": 0,
    "Override_AbnormalDispID_Victim": 0
  },
  "Name": "SK_GYCY_YouHun",
  "Label": "SK_GYCY_YouHun",
  "Type": "BOSS",
  "CoolDownRate": 50,
  "PlayTimeRate": 1.0,
  "XRateBig": 0.3,
  "ZRateBig": 0.1,
  "XRateSmall": 2.0,
  "Level1Scale": 1.0,
  "Level2Scale": 1.0,
  "Skills": [
    {
      "HitCount": 0,
      "PlayTimeRate": 1.0,
      "Id": 103921,
      "CanBreak": true,
      "Name": "未命名",
      "Description": "空",
      "AnimPath": null,
      "Buffers": null,
      "Buffs": null,
      "Bullets": null,
      "Key": "",
      "Step": 0,
      "StepCount": 0,
      "IsMimicry": false
    },
    {
      "HitCount": 0,
      "PlayTimeRate": 1.0,
      "Id": 103922,
      "CanBreak": true,
      "Name": "未命名",
      "Description": "空",
      "AnimPath": null,
      "Buffers": null,
      "Buffs": null,
      "Bullets": null,
      "Key": "",
      "Step": 0,
      "StepCount": 0,
      "IsMimicry": false
    },
    {
      "HitCount": 0,
      "PlayTimeRate": 1.0,
      "Id": 103923,
      "CanBreak": true,
      "Name": "未命名",
      "Description": "空",
      "AnimPath": null,
      "Buffers": null,
      "Buffs": null,
      "Bullets": null,
      "Key": "",
      "Step": 0,
      "StepCount": 0,
      "IsMimicry": false
    },
    {
      "HitCount": 0,
      "PlayTimeRate": 1.0,
      "Id": 103924,
      "CanBreak": true,
      "Name": "未命名",
      "Description": "空",
      "AnimPath": null,
      "Buffers": null,
      "Buffs": null,
      "Bullets": null,
      "Key": "",
      "Step": 0,
      "StepCount": 0,
      "IsMimicry": false
    },
    {
      "HitCount": 0,
      "PlayTimeRate": 1.0,
      "Id": 103931,
      "CanBreak": true,
      "Name": "未命名",
      "Description": "空",
      "AnimPath": null,
      "Buffers": null,
      "Buffs": null,
      "Bullets": null,
      "Key": "",
      "Step": 0,
      "StepCount": 0,
      "IsMimicry": false
    },
    {
      "HitCount": 0,
      "PlayTimeRate": 1.0,
      "Id": 103932,
      "CanBreak": true,
      "Name": "未命名",
      "Description": "空",
      "AnimPath": null,
      "Buffers": null,
      "Buffs": null,
      "Bullets": null,
      "Key": "",
      "Step": 0,
      "StepCount": 0,
      "IsMimicry": false
    },
    {
      "HitCount": 0,
      "PlayTimeRate": 1.0,
      "Id": 103950,
      "CanBreak": true,
      "Name": "未命名",
      "Description": "空",
      "AnimPath": null,
      "Buffers": null,
      "Buffs": null,
      "Bullets": null,
      "Key": "",
      "Step": 0,
      "StepCount": 0,
      "IsMimicry": false
    },
    {
      "HitCount": 0,
      "PlayTimeRate": 1.0,
      "Id": 103951,
      "CanBreak": true,
      "Name": "未命名",
      "Description": "空",
      "AnimPath": null,
      "Buffers": null,
      "Buffs": null,
      "Bullets": null,
      "Key": "",
      "Step": 0,
      "StepCount": 0,
      "IsMimicry": false
    },
    {
      "HitCount": 0,
      "PlayTimeRate": 1.0,
      "Id": 103952,
      "CanBreak": true,
      "Name": "未命名",
      "Description": "空",
      "AnimPath": null,
      "Buffers": null,
      "Buffs": null,
      "Bullets": null,
      "Key": "",
      "Step": 0,
      "StepCount": 0,
      "IsMimicry": false
    },
    {
      "HitCount": 0,
      "PlayTimeRate": 1.0,
      "Id": 103953,
      "CanBreak": true,
      "Name": "未命名",
      "Description": "空",
      "AnimPath": null,
      "Buffers": null,
      "Buffs": null,
      "Bullets": null,
      "Key": "",
      "Step": 0,
      "StepCount": 0,
      "IsMimicry": false
    },
    {
      "HitCount": 0,
      "PlayTimeRate": 1.0,
      "Id": 103960,
      "CanBreak": true,
      "Name": "未命名",
      "Description": "空",
      "AnimPath": null,
      "Buffers": null,
      "Buffs": null,
      "Bullets": null,
      "Key": "",
      "Step": 0,
      "StepCount": 0,
      "IsMimicry": false
    },
    {
      "HitCount": 0,
      "PlayTimeRate": 1.0,
      "Id": 103990,
      "CanBreak": true,
      "Name": "未命名",
      "Description": "空",
      "AnimPath": null,
      "Buffers": null,
      "Buffs": null,
      "Bullets": null,
      "Key": "",
      "Step": 0,
      "StepCount": 0,
      "IsMimicry": false
    },
    {
      "HitCount": 0,
      "PlayTimeRate": 1.0,
      "Id": 103998,
      "CanBreak": true,
      "Name": "未命名",
      "Description": "空",
      "AnimPath": null,
      "Buffers": null,
      "Buffs": null,
      "Bullets": null,
      "Key": "",
      "Step": 0,
      "StepCount": 0,
      "IsMimicry": false
    },
    {
      "HitCount": 0,
      "PlayTimeRate": 1.0,
      "Id": 103999,
      "CanBreak": true,
      "Name": "未命名",
      "Description": "空",
      "AnimPath": null,
      "Buffers": null,
      "Buffs": null,
      "Bullets": null,
      "Key": "",
      "Step": 0,
      "StepCount": 0,
      "IsMimicry": false
    }
  ],
  "DisableDepthOfField": false,
  "TransDone": null,
  "XRate": 0.0,
  "ZRate": 0.0,
  "Author": "神秘人物"
}