{
  "Name": "沙二郎",
  "Label": "SK_HFM_FuZiShu",
  "Type": "MAGIC",
  "XRateBig": 0.3,
  "ZRateBig": 0.1,
  "XRate": -400,
  "ZRate": 100,
  "CoolDownRate": 50,
  "XRateSmall": 2,
  "Level1Scale": 1,
  "Level2Scale": 2.2,
  "EnterSkill": {
    "Id": 8463
  },
  "TransDone": {
    "Buffers": [
      1000095
    ]
  },
  "Skills": [
    {
      "Key": "",
      "Id": 202501,
      "Name": "前摇+捅一下，再一顿砸"
    },
    {
      "Key": "",
      "Id": 202503,
      "Name": "后退前摇+上去打两下"
    },
    {
      "Key": "XBUTTON1",
      "Step": 1,
      "Id": 202504,
      "Name": "抡大锤子，然后跳起来锤"
    },
    {
      "Key": "XBUTTON1",
      "Step": 2,
      "Id": 202534,
      "Name": "抡大锤子，然后跳起来锤"
    },
    {
      "Key": "S+XBUTTON1",
      "Step": 1,
      "Id": 202506,
      "Name": "轮大锤子爆炸,再突进横扫"
    },
    {
      "Key": "S+XBUTTON1",
      "Step": 2,
      "Id": 202536,
      "Name": "轮大锤子爆炸,再突进横扫"
    },
    {
      "Key": "XBUTTON2",
      "Id": 11363,
      "Name": "精魄技能"
    },
    {
      "Key": "S+XBUTTON2",
      "Id": 202533,
      "Name": "前摇，+向前冲，一阵锤"
    },
    {
      "Key": "LBUTTON",
      "Id": 202514,
      "Name": "砸出一行地爆"
    },
    {
      "Key": "S+LBUTTON",
      "Id": 202518,
      "Name": "扔锤子出去砸人，然后突进上去拿锤子一阵砸"
    },
    {
      "Key": "S+RBUTTON",
      "Id": 202515,
      "Name": "冲上去，大锤子连续砸很多下"
    },
    {
      "Key": "RBUTTON",
      "Id": 202502,
      "Name": "横扫"
    },
    {
      "Key": "A+RBUTTON",
      "Id": 202517,
      "Name": "跳起来突进，砸出大地爆"
    },
    {
      "Key": "A+X",
      "Id": 202513,
      "Name": "放远程剑气"
    },
    {
      "Key": "SPACE",
      "Id": 202530,
      "Name": "后退"
    },
    {
      "Key": "",
      "Id": 202531,
      "Name": "扔锤子出去砸人，然后突进上去拿锤子一阵砸"
    },
    {
      "Key": "",
      "Id": 202533,
      "Name": "后退前摇+上去打两下"
    },
    {
      "Key": "",
      "Id": 202543,
      "Name": "回身"
    },
    {
      "Key": "",
      "Id": 202541,
      "Name": "前摇+磕头+后摇"
    },
    {
      "Key": "",
      "Id": 202542,
      "Name": "前摇+磕头+后摇"
    },
    {
      "Key": "",
      "Id": 412541,
      "Name": "前摇+磕头+后摇"
    },
    {
      "Key": "",
      "Id": 412542,
      "Name": "前摇+磕头+后摇"
    },
    {
      "Key": "",
      "Id": 202562,
      "Name": "放霸气,进二阶段"
    }
  ]
}